{
  "general": {
    "error": "エラー",
    "success": "成功",
    "cancel": "キャンセル",
    "submit": "送信",
    "submitting": "送信中...",
    "processing": "処理中...",
    "update": "更新",
    "updating": "更新中...",
    "delete": "削除",
    "next": "次へ",
    "save": "保存",
    "undo": "元に戻す",
    "sending": "送信中...",
    "from": "開始：",
    "to": "終了：",
    "start": "開始：",
    "end": "終了：",
    "startDate": "開始日",
    "endDate": "終了日",
    "monday": "月曜日",
    "tuesday": "火曜日",
    "wednesday": "水曜日",
    "thursday": "木曜日",
    "friday": "金曜日",
    "saturday": "土曜日",
    "sunday": "日曜日",
    "mondayShort": "月",
    "tuesdayShort": "火",
    "wednesdayShort": "水",
    "thursdayShort": "木",
    "fridayShort": "金",
    "saturdayShort": "土",
    "sundayShort": "日"
  },
  "profile": {
    "accountSettings": "アカウント設定",
    "deleteAccount": "アカウント削除",
    "deleteAccountConfirmation": "アカウントを削除してもよろしいですか？この操作は元に戻せません。すべてのデータが完全に削除されます。\n\nアカウントを認証して続行してください：",
    "accountDeletionInProgress": "削除中...",
    "accountDeleted": "アカウントが削除されました",
    "accountDeletionFailed": "アカウントの削除に失敗しました",
    "reauthenticationSuccess": "認証に成功しました。アカウントを削除できます。",
    "inviteOtherParent": "他の保護者を招待",
    "familyId": "ファミリーID：{{familyId}}",
    "displayName": "表示名",
    "enterDisplayName": "表示名を入力してください",
    "notifications": "通知",
    "newJournalEntries": "新しい日誌の記録",
    "newScheduleRequests": "新しいスケジュールリクエスト",
    "schoolTimes": "学校時間",
    "selected": "選択：{{start}} - {{end}}",
    "displaySchoolTimesInCalendar": "カレンダーに学校時間を表示",
    "language": "言語",
    "logout": "ログアウト",
    "inviteModalTitle": "他の保護者を招待",
    "inviteModalBody": "招待する保護者のメールアドレスを入力してください：",
    "enterEmailAddress": "メールアドレスを入力",
    "sendInvitation": "送信",
    "enterEmailError": "メールアドレスを入力してください",
    "familyIdNotAvailable": "ファミリーIDが利用できません",
    "invitationSent": "招待が正常に送信されました",
    "invitationFailed": "招待の送信に失敗しました",
    "logoutFailed": "ログアウトに失敗しました",
    "profileUpdated": "プロフィールが更新されました",
    "profileUpdateFailed": "プロフィールの更新に失敗しました",
    "notificationPermissionRequired": "通知の許可が必要です",
    "notificationPermissionMessage": "通知を受け取るには、端末の設定で有効にしてください：\n\n1. 設定 > CoPals\n2. 「通知を許可」を有効にする\n3. アプリに戻って再試行してください",
    "openSettings": "設定を開く",
    "settingsInstructions": "設定アプリ > CoPals > 通知を開いて有効にしてください。",
    "inviteEmailSubject": "CoPalsへの招待",
    "inviteEmailText": "あなたはCoPalsアプリでファミリーに招待されました。あなたのファミリーIDは：{{familyId}}です。登録時にこのIDを使用してください。",
    "inviteEmailTitle": "CoPalsファミリーへの招待",
    "inviteEmailIntro": "この招待を受け取るには：",
    "inviteEmailStep1": "以下からアプリをダウンロードしてインストールしてください：",
    "inviteEmailStep2": "このメールアドレスでアカウントを作成してください：<strong>{{email}}</strong>",
    "inviteEmailAppleWarning": "Appleログインを使用する場合、「メールを非表示」を選択しないでください",
    "inviteEmailStep3": "「既存のファミリーに参加」を選択し、求められたら、このファミリーIDを入力してください：<strong>{{familyId}}</strong>",
    "inviteEmailFooter": "この招待はあなたのメールアドレス専用です。他の人や別のアドレスでは使用できません。"
  },
  "requests": {
    "loadingRequests": "リクエストを読み込み中...",
    "approved": "承認済み",
    "declined": "却下",
    "pending": "保留中",
    "swapDaysRequest": "日付交換リクエスト",
    "holidaysRequest": "休暇リクエスト",
    "deleteScheduleRequest": "スケジュール削除リクエスト",
    "regularScheduleRequest": "定期スケジュールリクエスト",
    "status": "ステータス：{{status}}",
    "statusOn": "ステータス：{{status}}（{{date}}）",
    "requestedBy": "リクエスト者：{{name}}",
    "requested": "リクエスト日：{{date}}",
    "approve": "承認",
    "decline": "却下",
    "close": "閉じる",
    "scheduleId": "スケジュールID：{{id}}",
    "updated": "更新日：{{date}}",
    "week": "週{{number}}",
    "at": "時刻",
    "holidayTimeFrom": "休暇期間開始",
    "until": "まで",
    "willHaveDaysFrom": "{{name}}は{{startDate}}から日があります",
    "isRequestingHolidayFrom": "{{name}}は{{startDate}}から休暇を申請しています",
    "requestToDeleteRepeating": "{{startDate}}から{{endDate}}まで、{{cadence}}ごとに繰り返すスケジュールの削除リクエスト",
    "newRepeatingSchedule": "{{startDate}}から{{endDate}}まで、{{cadence}}ごとに新しい繰り返しスケジュール",
    "oneWeek": "1週間",
    "twoWeeks": "2週間",
    "fourWeeks": "4週間",
    "failedToLoadRequests": "リクエストの読み込みに失敗しました",
    "familyIdNotFound": "ファミリーIDが見つかりません",
    "requestApproved": "リクエストが承認されました",
    "requestDeclined": "リクエストが却下されました",
    "failedToUpdateRequest": "リクエストの更新に失敗しました",
    "failedToListenForUpdates": "リクエストの更新を取得できませんでした"
  },
  "navigation": {
    "calendar": "カレンダー",
    "journal": "日誌",
    "requests": "リクエスト",
    "profile": "プロフィール"
  },
  "calendar": {
    "regularSchedule": "定期スケジュール",
    "swapDays": "日付交換",
    "holidays": "休暇",
    "createSchedule": "スケジュール作成",
    "setHandoverTimes": "引き渡し時間を設定",
    "swapDaysRequest": "日付交換リクエスト",
    "holidaysRequest": "休暇リクエスト",
    "deleteSchedule": "スケジュール削除",
    "selectRepeat": "スケジュールの繰り返し頻度を選択してください：",
    "selectDays": "子どもと過ごす夜の日を選択してください：",
    "holidayPeriod": "休暇期間",
    "noHandoversRequired": "このスケジュールには引き渡しは不要です。",
    "handoverTime": "引き渡し時間：",
    "handoverAt": "引き渡し時間：",
    "week": "週",
    "oneWeekRepeating": "1週間ごとに繰り返し",
    "twoWeeksRepeating": "2週間ごとに繰り返し",
    "fourWeeksRepeating": "4週間ごとに繰り返し",
    "submitSwapRequest": "日付交換リクエストを送信",
    "submitHolidayRequest": "休暇リクエストを送信",
    "requestDaySwap": "日付交換リクエスト",
    "deleteScheduleButton": "スケジュールを削除...",
    "deleteRegularSchedule": "定期スケジュールを削除",
    "deleteSwapSchedule": "日付交換スケジュールを削除",
    "deleteHolidaySchedule": "休暇スケジュールを削除",
    "with": "と一緒に",
    "isRequestingDays": "日を希望しています：",
    "inExchange": "交換として、",
    "loadingScheduleData": "スケジュールデータを読み込み中...",
    "otherParent": "他の保護者",
    "requestSubmitted": "リクエストが送信されました。",
    "deleteRequestSubmitted": "削除リクエストが送信されました。",
    "failedToSubmit": "送信に失敗しました",
    "failedToRequestDeletion": "スケジュール削除リクエストに失敗しました",
    "scheduleMissing": "スケジュールデータがありません",
    "failedToLoadForDeletion": "削除用スケジュールの読み込みに失敗しました"
  },
  "journal": {
    "meal": "食事",
    "medication": "薬",
    "note": "メモ",
    "entryTitle": "記録",
    "medicationEntry": "薬の記録",
    "noteEntry": "メモの記録",
    "editEntry": "記録を編集",
    "time": "時間",
    "name": "名前",
    "dose": "量",
    "singleDose": "単回量",
    "cadenceHours": "間隔（時間）",
    "durationDays": "期間（日）",
    "title": "タイトル",
    "enterDescription": "説明を入力してください（例：ミルク入りシリアル）",
    "enterMedicationName": "薬の名前を入力してください",
    "enterDose": "量を入力してください（例：500mg）",
    "enterNoteTitle": "メモのタイトルを入力してください",
    "enterNoteDescription": "メモの説明を入力してください",
    "untitled": "タイトルなし",
    "noDescription": "説明なし",
    "noTime": "時間なし",
    "breakfast": "朝食",
    "morningSnack": "午前のおやつ",
    "lunch": "昼食",
    "afternoonSnack": "午後のおやつ",
    "dinner": "夕食",
    "nightSnack": "夜のおやつ",
    "with": "と一緒に",
    "medicationDose": "薬の量",
    "noteBy": "記録者",
    "dosage": "投与量",
    "fillAllFields": "すべての項目を入力してください。",
    "entryExists": "記録はすでに存在します。",
    "saveFailed": "日誌の保存に失敗しました。",
    "entryUpdated": "記録が更新されました。",
    "entryDeleted": "記録が削除されました。",
    "updateFailed": "記録の更新に失敗しました。",
    "deleteFailed": "記録の削除に失敗しました。"
  },
  "auth": {
    "existingAccount": "既存のアカウント",
    "newAccount": "新しいアカウント",
    "email": "メールアドレス",
    "password": "パスワード",
    "confirmPassword": "パスワード確認",
    "forgotPassword": "パスワードを忘れましたか？",
    "logIn": "ログイン",
    "signUp": "新規登録",
    "orSignInWith": "または次でログイン",
    "emailRequired": "メールアドレスが必要です",
    "enterEmailFirst": "まずメールアドレスを入力してください",
    "invalidEmail": "無効なメールアドレス",
    "enterValidEmail": "有効なメールアドレスを入力してください",
    "passwordMismatch": "パスワードが一致しません",
    "passwordsDoNotMatch": "パスワードが一致しません。確認して再入力してください。",
    "signupError": "登録エラー",
    "loginError": "ログインエラー",
    "passwordReset": "パスワードリセット",
    "resetEmailSent": "リセットメールが{{email}}に送信されました",
    "verifyEmailTitle": "メールアドレスを確認",
    "verifyEmailMessage": "メールを確認してアカウントを認証してください。",
    "verifiedEmail": "メール認証済み",
    "notVerified": "未認証",
    "verifyBeforeContinuing": "続行する前にメールを認証してください",
    "enterDisplayName": "表示名を入力してください",
    "yourName": "あなたの名前",
    "saveNameError": "名前の保存に失敗しました",
    "familySetup": "ファミリー設定",
    "joinExistingFamily": "既存のファミリーに参加",
    "createNewFamily": "新しいファミリーを作成",
    "enterFamilyId": "ファミリーIDを入力",
    "enterYourFamilyName": "あなたのファミリー名を入力してください",
    "familyName": "ファミリー名",
    "familyNameTooShort": "ファミリー名は2文字以上必要です",
    "familyIdPatternDetected": "これは既存のファミリーIDのようです。ファミリーに参加しようとしていますか？",
    "joining": "参加中...",
    "familyIdNotFound": "ファミリーIDが見つかりません",
    "emailNotInvited": "このメールアドレスはこのファミリーに招待されていません",
    "failedToJoinFamily": "ファミリーへの参加に失敗しました：{{message}}",
    "creating": "作成中...",
    "failedToCreateFamily": "ファミリーの作成に失敗しました：{{message}}",
    "developmentMode": "開発モード",
    "googleSignInNotAvailable": "Expo GoではGoogleサインインは利用できません。メール/パスワード認証を使用するか、開発ビルドでテストしてください。",
    "notAvailable": "利用できません",
    "appleSignInNotAvailable": "このデバイスではAppleサインインは利用できません",
    "appleSignInError": "Appleサインインエラー",
    "appleSignInFailed": "Appleサインインに失敗しました",
    "signInAlreadyInProgress": "サインインはすでに進行中です。",
    "playServicesNotAvailable": "Google Playサービスが利用できないか、古いバージョンです。",
    "googleSignInError": "Googleサインインエラー",
    "errorOccurred": "エラーが発生しました：{{message}}",
    "failedToCheckVerification": "メール認証状況の確認に失敗しました"
  },
  "appstore": {
    "appname": "CoPals",
    "shortDescription": "分離した親のためのすべてを含むアプリ",
    "fullDescription": "子どものカレンダー、日誌、スケジューラーを含む。分離した親のためのコパレンディングを簡素化します。 サブスクリプションやアプリ内課金はありません。",
    "keywords": "分離した親, コパレンディング, コパレンディング, 子ども, カレンダー, 日誌, スケジューラー"
  }
}